task1/rom.sv
module rom #(
    parameter   ADDRESS_WIDTH = 8,
                DATA_WIDTH = 8
)(
    input logic                      clk,
    input logic [ADDRESS_WIDTH-1:0] addr,
    output logic [DATA_WIDTH-1:0]   dout
);

logic [DATA_WIDTH-1:0] rom_array [2**ADDRESS_WIDTH-1:0];

initial begin
    $display("Loading rom.");
    $readmemh("sinerom.mem", rom_array);
end;

always_ff @(posedge clk)
    // output is synchronous
    dout <= rom_array [addr];

endmodule

task1/counter.sv
module counter #(
    parameter WIDTH = 8
)(
    // interface signals
    input logic clk, //clock
    input logic rst, //reset
    input logic en, //counter enable
    input logic [WIDTH-1:0] incr,
    output logic [WIDTH-1:0] count //address output
);

always_ff @ (posedge clk)
    if (rst) count <= {WIDTH{1'b0}};
    else count <= incr + {{WIDTH-1{1'b0}},en};

endmodule

task1/sinegen.sv
module sinegen #(
    parameter   A_WIDTH = 8,
                D_WIDTH = 8
)(
    // interface signals
    input   logic                       clk,        // clock
    input   logic                       rst,        // reset
    input   logic                       en,         // enable
    input   logic [D_WIDTH-1:0]         incr,       // increment for addr counter
    output  logic [D_WIDTH-1:0]         dout        // output data
);

    logic   [A_WIDTH-1:0]       address;    // interconnect wire

counter addrCounter(
    .clk (clk),
    .rst (rst),
    .en (en),
    .incr (incr),
    .count (address)
);

rom sineRom(
    .clk (clk),
    .addr (address),
    .dout (dout)
);

endmodule

task1/sinegen.vcd
$version Generated by VerilatedVcd $end
$date Thu Oct 27 10:39:00 2022 $end
$timescale 1ps $end

 $scope module TOP $end
  $var wire  1 # clk $end
  $var wire  8 ' dout [7:0] $end
  $var wire  1 % en $end
  $var wire  8 & incr [7:0] $end
  $var wire  1 $ rst $end
  $scope module sinegen $end
   $var wire 32 ) A_WIDTH [31:0] $end
   $var wire 32 ) D_WIDTH [31:0] $end
   $var wire  8 ( address [7:0] $end
   $var wire  1 # clk $end
   $var wire  8 ' dout [7:0] $end
   $var wire  1 % en $end
   $var wire  8 & incr [7:0] $end
   $var wire  1 $ rst $end
   $scope module addrCounter $end
    $var wire 32 ) WIDTH [31:0] $end
    $var wire  1 # clk $end
    $var wire  8 ( count [7:0] $end
    $var wire  1 % en $end
    $var wire  8 & incr [7:0] $end
    $var wire  1 $ rst $end
   $upscope $end
   $scope module sineRom $end
    $var wire 32 ) ADDRESS_WIDTH [31:0] $end
    $var wire 32 ) DATA_WIDTH [31:0] $end
    $var wire  8 ( addr [7:0] $end
    $var wire  1 # clk $end
    $var wire  8 ' dout [7:0] $end
   $upscope $end
  $upscope $end
 $upscope $end
$enddefinitions $end


#0
1#
0$
1%
b00000001 &
b00000000 '
b00000000 (
b00000000000000000000000000001000 )
#1
0#
#2
1#
b00000110 &
b11111110 '
b00000001 (
#3
0#
#4
1#
b11111101 '
b00000111 (
#5
0#
#6
1#
b11111100 '
b00001101 (
#7
0#
#8
1#
b11110111 '
b00010011 (
#9
0#
#10
1#
b11110000 '
b00011001 (
#11
0#
#12
1#
b11100110 '
b00011111 (
#13
0#
#14
1#
b11011010 '
b00100101 (
#15
0#
#16
1#
b11001101 '
b00101011 (
#17
0#
#18
1#
b10111101 '
b00110001 (
#19
0#
#20
1#
b10101100 '
b00110111 (
#21
0#
#22
1#
b10011010 '
b00111101 (
#23
0#
#24
1#
b10001000 '
b01000011 (
#25
0#
#26
1#
b01110101 '
b01001001 (
#27
0#
#28
1#
b01100011 '
b01001111 (
#29
0#
#30
1#
b01010001 '
b01010101 (
#31
0#
#32
1#
b01000000 '
b01011011 (
#33
0#
#34
1#
b00110000 '
b01100001 (
#35
0#
#36
1#
b00100011 '
b01100111 (
#37
0#
#38
1#
b00010111 '
b01101101 (
#39
0#
#40
1#
b00001101 '
b01110011 (
#41
0#
#42
1#
b00000110 '
b01111001 (
#43
0#
#44
1#
b00000001 '
b01111111 (
#45
0#
#46
1#
b00000000 '
b10000101 (
#47
0#
#48
1#
b10001011 (
#49
0#
#50
1#
b00000100 '
b10010001 (
#51
0#
#52
1#
b00001010 '
b10010111 (
#53
0#
#54
1#
b00010011 '
b10011101 (
#55
0#
#56
1#
b00011110 '
b10100011 (
#57
0#
#58
1#
b00101100 '
b10101001 (
#59
0#
#60
1#
b00111011 '
b10101111 (
#61
0#
#62
1#
b01001011 '
b10110101 (
#63
0#
#64
1#
b01011101 '
b10111011 (
#65
0#
#66
1#
b01101111 '
b11000001 (
#67
0#
#68
1#
b10000010 '
b11000111 (
#69
0#
#70
1#
b10010100 '
b11001101 (
#71
0#
#72
1#
b10100110 '
b11010011 (
#73
0#
#74
1#
b10111000 '
b11011001 (
#75
0#
#76
1#
b11001000 '
b11011111 (
#77
0#
#78
1#
b11010110 '
b11100101 (
#79
0#
#80
1#
b11100011 '
b11101011 (
#81
0#
#82
1#
b11101101 '
b11110001 (
#83
0#
#84
1#
b11110101 '
b11110111 (
#85
0#
#86
1#
b11111010 '
b11111101 (
#87
0#
#88
1#
b11111101 '
b00000011 (
#89
0#
#90
1#
b00001001 (
#91
0#
#92
1#
b11111010 '
b00001111 (
#93
0#
#94
1#
b11110101 '
b00010101 (
#95
0#
#96
1#
b11101101 '
b00011011 (
#97
0#
#98
1#
b11100011 '
b00100001 (
#99
0#
#100
1#
b11010110 '
b00100111 (
#101
0#
#102
1#
b11001000 '
b00101101 (
#103
0#
#104
1#
b10111000 '
b00110011 (
#105
0#
#106
1#
b10100110 '
b00111001 (
#107
0#
#108
1#
b10010100 '
b00111111 (
#109
0#
#110
1#
b10000010 '
b01000101 (
#111
0#
#112
1#
b01101111 '
b01001011 (
#113
0#
#114
1#
b01011101 '
b01010001 (
#115
0#
#116
1#
b01001011 '
b01010111 (
#117
0#
#118
1#
b00111011 '
b01011101 (
#119
0#
#120
1#
b00101100 '
b01100011 (
#121
0#
#122
1#
b00011110 '
b01101001 (
#123
0#
#124
1#
b00010011 '
b01101111 (
#125
0#
#126
1#
b00001010 '
b01110101 (
#127
0#
#128
1#
b00000100 '
b01111011 (
#129
0#
#130
1#
b00000000 '
b10000001 (
#131
0#
#132
1#
b10000111 (
#133
0#
#134
1#
b00000001 '
b10001101 (
#135
0#
#136
1#
b00000110 '
b10010011 (
#137
0#
#138
1#
b00001101 '
b10011001 (
#139
0#
#140
1#
b00010111 '
b10011111 (
#141
0#
#142
1#
b00000101 &
b00100011 '
b10100101 (
#143
0#
#144
1#
b00110000 '
b10101010 (
#145
0#
#146
1#
b00111101 '
b10101111 (
#147
0#
#148
1#
b00000100 &
b01001011 '
b10110100 (
#149
0#
#150
1#
b01011010 '
b10111000 (
#151
0#
#152
1#
b00000011 &
b01100110 '
b10111100 (
#153
0#
#154
1#
b01110010 '
b10111111 (
#155
0#
#156
1#
b00000010 &
b01111011 '
b11000010 (
#157
0#
#158
1#
b00000001 &
b10000101 '
b11000100 (
#159
0#
#160
1#
b10001011 '
b11000101 (
#161
0#
#162
1#
b10001110 '
b11000110 (
#163
0#
#164
1#
b10010001 '
b11000111 (
#165
0#
#166
1#
b00000000 &
b10010100 '
b11001000 (
#167
0#
#168
1#
b10010111 '
